{
  "id": "site/node_modules/@docusaurus/logger/README",
  "title": "@docusaurus/logger",
  "description": "An encapsulated logger for semantically formatting console messages.",
  "source": "@site/node_modules/@docusaurus/logger/README.md",
  "sourceDirName": "site/node_modules/@docusaurus/logger",
  "slug": "/site/node_modules/@docusaurus/logger/",
  "permalink": "/family-cfo/site/node_modules/@docusaurus/logger/",
  "draft": false,
  "unlisted": false,
  "tags": [],
  "version": "current",
  "frontMatter": {}
}